<frameset>
  <predicate lemma="coil">
    <roleset id="coil.01" name="(cause to) be coiled">
      <roles>
        <role descr="causer of coiling" f="pag" n="0"/>
        <role descr="coiled thing" f="ppt" n="1"/>
        <role descr="secondary attribute, coiled around what" f="loc" n="2"/>
      </roles>
    </roleset>
  </predicate>
  <predicate lemma="coil_up">
    <roleset id="coil_up.02" name="exist in coiled state">
      <roles>
        <role descr="coiled entity" f="ppt" n="1"/>
      </roles>
    </roleset>
  </predicate>
</frameset>
