<frameset>
  <predicate lemma="enter">
    <roleset id="enter.01" name="enter, go in">
      <roles>
        <role descr="entity entering" f="ppt" n="0"/>
        <role descr="place or thing entered" f="loc" n="1"/>
      </roles>
    </roleset>
    <roleset id="enter.02" name="submit something">
      <roles>
        <role descr="submitter" f="pag" n="0"/>
        <role descr="thing submitted" f="ppt" n="1"/>
        <role descr="submitted to" f="loc" n="2"/>
        <role descr="benefactive" f="gol" n="3"/>
      </roles>
    </roleset>
  </predicate>
  <predicate lemma="entrance">
    <roleset id="entrance.03" name="put into a trance-like state">
      <roles>
        <role descr="causer of trance, agent" f="pag" n="0"/>
        <role descr="victim" f="ppt" n="1"/>
        <role descr="instrument, when separate from arg 0" f="mnr" n="2"/>
      </roles>
    </roleset>
  </predicate>
</frameset>
